dictionary/__init__.py
dictionary/dictionary.py
cs453_adem_buran_dictionary2-2.0.0.dist-info/METADATA
cs453_adem_buran_dictionary2-2.0.0.dist-info/WHEEL
cs453_adem_buran_dictionary2-2.0.0.dist-info/top_level.txt
cs453_adem_buran_dictionary2-2.0.0.dist-info/RECORD
