Metadata-Version: 2.1
Name: cs453-adem-buran-dictionary2
Version: 2.0.0
Summary: UNKNOWN
Author: Emin Adem Buran
License: UNKNOWN
Platform: UNKNOWN
Requires-Python: >=3.8
Requires-Dist: requests (>=2.23.0)
